kp_test/__init__.py
kp_test/print_test.py
kp_test-0.0.3.dist-info/LICENSE.txt
kp_test-0.0.3.dist-info/METADATA
kp_test-0.0.3.dist-info/WHEEL
kp_test-0.0.3.dist-info/top_level.txt
kp_test-0.0.3.dist-info/RECORD
